JXTABLES/BaseHandler.py
JXTABLES/CircularBuffer.py
JXTABLES/ClientStatistics.py
JXTABLES/ClientStatistics_pb2.py
JXTABLES/PingResponse.py
JXTABLES/SubscribeHandler.py
JXTABLES/TempConnectionManager.py
JXTABLES/XDashDebugger.py
JXTABLES/XDashDebugger_pb2.py
JXTABLES/XTableProto_pb2.py
JXTABLES/XTableValues_pb2.py
JXTABLES/XTableValues_pb2_grpc.py
JXTABLES/XTablesByteUtils.py
JXTABLES/XTablesClient.py
JXTABLES/XTablesSocketMonitor.py
JXTABLES/__init__.py
xtablesclient-5.7.9.dist-info/METADATA
xtablesclient-5.7.9.dist-info/WHEEL
xtablesclient-5.7.9.dist-info/top_level.txt
xtablesclient-5.7.9.dist-info/RECORD
